lamd/__init__.py
lamd/__main__.py
lamd/add_section.py
lamd/clean_yaml_refs.py
lamd/dependencies.py
lamd/extractdate_talk.py
lamd/flags.py
lamd/makecv.py
lamd/makedependency_talk.py
lamd/makediagdependency_talk.py
lamd/maketalk.py
lamd/mdfield.py
lamd/mdlist.py
lamd/mdpp.py
lamd/ndlml.py
lamd/macros/color-scheme.gpp
lamd/macros/svgi-includes.gpp
lamd/macros/talk-logos.gpp
lamd/macros/talk-macros-back.gpp
lamd/macros/talk-macros-code.gpp
lamd/macros/talk-macros-docx.gpp
lamd/macros/talk-macros-draft.gpp
lamd/macros/talk-macros-edit.gpp
lamd/macros/talk-macros-exercises.gpp
lamd/macros/talk-macros-front.gpp
lamd/macros/talk-macros-html.gpp
lamd/macros/talk-macros-include.gpp
lamd/macros/talk-macros-ipynb.gpp
lamd/macros/talk-macros-notes-docx.gpp
lamd/macros/talk-macros-notes-html.gpp
lamd/macros/talk-macros-notes-ipynb.gpp
lamd/macros/talk-macros-notes-tex.gpp
lamd/macros/talk-macros-notes.gpp
lamd/macros/talk-macros-null.gpp
lamd/macros/talk-macros-pptx.gpp
lamd/macros/talk-macros-slides-html.gpp
lamd/macros/talk-macros-slides-ipynb.gpp
lamd/macros/talk-macros-slides-pptx.gpp
lamd/macros/talk-macros-slides-svg.gpp
lamd/macros/talk-macros-slides-tex.gpp
lamd/macros/talk-macros-slides.gpp
lamd/macros/talk-macros-svg.gpp
lamd/macros/talk-macros-tex.gpp
lamd/macros/talk-macros.gpp
lamd/macros/talk-people.gpp
makemd/__init__.py
makemd/__main__.py
makemd/add_section.py
makemd/clean_yaml_refs.py
makemd/dependencies.py
makemd/extractdate_talk.py
makemd/flags.py
makemd/makecv.py
makemd/makedependency_talk.py
makemd/makediagdependency_talk.py
makemd/maketalk.py
makemd/mdfield.py
makemd/mdlist.py
makemd/mdpp.py
makemd/ndlml.py
makemd/macros/color-scheme.gpp
makemd/macros/svgi-includes.gpp
makemd/macros/talk-logos.gpp
makemd/macros/talk-macros-back.gpp
makemd/macros/talk-macros-code.gpp
makemd/macros/talk-macros-docx.gpp
makemd/macros/talk-macros-draft.gpp
makemd/macros/talk-macros-edit.gpp
makemd/macros/talk-macros-exercises.gpp
makemd/macros/talk-macros-front.gpp
lamd-0.1.2.dist-info/METADATA
lamd-0.1.2.dist-info/WHEEL
lamd-0.1.2.dist-info/dependency_links.txt
lamd-0.1.2.dist-info/entry_points.txt
lamd-0.1.2.dist-info/top_level.txt
lamd-0.1.2.dist-info/RECORD
